sphinx_webslides_builder/__init__.py
sphinx_webslides_builder/blockquote.py
sphinx_webslides_builder/common.py
sphinx_webslides_builder/description_list.py
sphinx_webslides_builder/div.py
sphinx_webslides_builder/figure.py
sphinx_webslides_builder/flexblock.py
sphinx_webslides_builder/font_awesome.py
sphinx_webslides_builder/header_footer.py
sphinx_webslides_builder/heading.py
sphinx_webslides_builder/hr.py
sphinx_webslides_builder/link.py
sphinx_webslides_builder/paragraph.py
sphinx_webslides_builder/preformatted.py
sphinx_webslides_builder/slide.py
sphinx_webslides_builder/span.py
sphinx_webslides_builder/video.py
sphinx_webslides_builder/web.py
sphinx_webslides_builder/webslides_builder.py
sphinx_webslides_builder/webslides_writer.py
sphinx_webslides_builder/themes/webslides_base/genindex.html
sphinx_webslides_builder/themes/webslides_base/layout.html
sphinx_webslides_builder/themes/webslides_base/page.html
sphinx_webslides_builder/themes/webslides_base/search.html
sphinx_webslides_builder/themes/webslides_base/theme.conf
sphinx_webslides_builder/themes/webslides_base/static/css/svg-icons.css
sphinx_webslides_builder/themes/webslides_base/static/css/webslides.css
sphinx_webslides_builder/themes/webslides_base/static/js/svg-icons.js
sphinx_webslides_builder/themes/webslides_base/static/js/webslides.js
sphinx_webslides_builder/themes/webslides_base/static/js/webslides.min.js
sphinx_webslides_builder-0.0.3.dist-info/LICENSE
sphinx_webslides_builder-0.0.3.dist-info/METADATA
sphinx_webslides_builder-0.0.3.dist-info/WHEEL
sphinx_webslides_builder-0.0.3.dist-info/entry_points.txt
sphinx_webslides_builder-0.0.3.dist-info/top_level.txt
sphinx_webslides_builder-0.0.3.dist-info/RECORD
